ultimate_mcp_server/__init__.py
ultimate_mcp_server/__main__.py
ultimate_mcp_server/config.py
ultimate_mcp_server/constants.py
ultimate_mcp_server/exceptions.py
ultimate_mcp_server/graceful_shutdown.py
ultimate_mcp_server/tool_token_counter.py
ultimate_mcp_server/working_memory_api.py
ultimate_mcp_server/cli/__init__.py
ultimate_mcp_server/cli/__main__.py
ultimate_mcp_server/cli/commands.py
ultimate_mcp_server/cli/helpers.py
ultimate_mcp_server/cli/typer_cli.py
ultimate_mcp_server/clients/__init__.py
ultimate_mcp_server/clients/completion_client.py
ultimate_mcp_server/clients/rag_client.py
ultimate_mcp_server/config/examples/filesystem_config.yaml
ultimate_mcp_server/core/__init__.py
ultimate_mcp_server/core/server.py
ultimate_mcp_server/core/state_store.py
ultimate_mcp_server/core/evaluation/base.py
ultimate_mcp_server/core/evaluation/evaluators.py
ultimate_mcp_server/core/providers/__init__.py
ultimate_mcp_server/core/providers/anthropic.py
ultimate_mcp_server/core/providers/base.py
ultimate_mcp_server/core/providers/deepseek.py
ultimate_mcp_server/core/providers/gemini.py
ultimate_mcp_server/core/providers/grok.py
ultimate_mcp_server/core/providers/ollama.py
ultimate_mcp_server/core/providers/openai.py
ultimate_mcp_server/core/providers/openrouter.py
ultimate_mcp_server/core/tournaments/manager.py
ultimate_mcp_server/core/tournaments/tasks.py
ultimate_mcp_server/core/tournaments/utils.py
ultimate_mcp_server/core/ums_api/__init__.py
ultimate_mcp_server/core/ums_api/ums_database.py
ultimate_mcp_server/core/ums_api/ums_endpoints.py
ultimate_mcp_server/core/ums_api/ums_models.py
ultimate_mcp_server/core/ums_api/ums_services.py
ultimate_mcp_server/services/__init__.py
ultimate_mcp_server/services/cache.py
ultimate_mcp_server/services/document.py
ultimate_mcp_server/services/prompts.py
ultimate_mcp_server/services/analytics/__init__.py
ultimate_mcp_server/services/analytics/metrics.py
ultimate_mcp_server/services/analytics/reporting.py
mseep_ultimate_mcp_server-0.1.7.dist-info/METADATA
mseep_ultimate_mcp_server-0.1.7.dist-info/WHEEL
mseep_ultimate_mcp_server-0.1.7.dist-info/entry_points.txt
mseep_ultimate_mcp_server-0.1.7.dist-info/licenses/LICENSE
mseep_ultimate_mcp_server-0.1.7.dist-info/RECORD
